ciscoaxl/__init__.py
ciscoaxl/axl.py
ciscoaxl/axl_generator.py
ciscoaxl/config.py
ciscoaxl/exceptions.py
ciscoaxl/helpers.py
ciscoaxl/schema/10.0/AXLAPI.wsdl
ciscoaxl/schema/10.0/AXLEnums.xsd
ciscoaxl/schema/10.0/AXLSoap.xsd
ciscoaxl/schema/10.5/AXLAPI.wsdl
ciscoaxl/schema/10.5/AXLEnums.xsd
ciscoaxl/schema/10.5/AXLSoap.xsd
ciscoaxl/schema/11.0/AXLAPI.wsdl
ciscoaxl/schema/11.0/AXLEnums.xsd
ciscoaxl/schema/11.0/AXLSoap.xsd
ciscoaxl/schema/11.5/AXLAPI.wsdl
ciscoaxl/schema/11.5/AXLEnums.xsd
ciscoaxl/schema/11.5/AXLSoap.xsd
ciscoaxl/schema/12.0/AXLAPI.wsdl
ciscoaxl/schema/12.0/AXLEnums.xsd
ciscoaxl/schema/12.0/AXLSoap.xsd
ciscoaxl/schema/12.5/AXLAPI.wsdl
ciscoaxl/schema/12.5/AXLEnums.xsd
ciscoaxl/schema/12.5/AXLSoap.xsd
ciscoaxl/schema/8.5/AXLAPI.wsdl
ciscoaxl/schema/8.5/AXLEnums.xsd
ciscoaxl/schema/8.5/AXLSoap.xsd
ciscoaxl/schema/9.1/AXLAPI.wsdl
ciscoaxl/schema/9.1/AXLEnums.xsd
ciscoaxl/schema/9.1/AXLSoap.xsd
ciscoaxl/schema/current/AXLAPI.wsdl
ciscoaxl/schema/current/AXLEnums.xsd
ciscoaxl/schema/current/AXLSoap.xsd
ciscoaxl/wsdl.py
ciscoaxl-0.164.dist-info/LICENSE
ciscoaxl-0.164.dist-info/METADATA
ciscoaxl-0.164.dist-info/WHEEL
ciscoaxl-0.164.dist-info/RECORD
