Metadata-Version: 2.1
Name: ciscoaxl
Version: 0.164
Summary: Cisco CUCM AXL Library. simple to use.
Home-page: https://github.com/levensailor/ciscoaxl
License: MIT
Keywords: Cisco,Call Manager,CUCM,AXL,VoIP
Author: Jeff Levensailor
Author-email: jeff@levensailor.com
Requires-Python: >=3.7,<4.0
Classifier: Development Status :: 5 - Production/Stable
Classifier: Intended Audience :: Developers
Classifier: License :: OSI Approved :: MIT License
Classifier: Operating System :: OS Independent
Classifier: Programming Language :: Python :: 3
Classifier: Programming Language :: Python :: 3.7
Classifier: Programming Language :: Python :: 3.8
Classifier: Programming Language :: Python :: 3.9
Classifier: Programming Language :: Python :: 3.10
Classifier: Programming Language :: Python :: 3.11
Provides-Extra: github
Requires-Dist: requests (>=2.27.1,<3.0.0)
Requires-Dist: termcolor (>=1.1.0,<2.0.0)
Requires-Dist: zeep (>=4.1.0,<5.0.0)
Project-URL: Repository, https://github.com/levensailor/ciscoaxl
